<?xml version="1.0" encoding="utf-8"?>
<!DOCTYPE hibernate-mapping PUBLIC "-//Hibernate/Hibernate Mapping DTD 3.0//EN"
"http://hibernate.sourceforge.net/hibernate-mapping-3.0.dtd">
<!-- 
    Mapping file autogenerated by MyEclipse Persistence Tools
-->
<hibernate-mapping>
    <class name="com.hcctech.bookshelf.pojo.BsEbook" table="bs_ebook" catalog="bookshelf_db">
        <id name="id" type="java.lang.Integer">
            <column name="id" />
            <generator class="native" />
        </id>
        <property name="bookCode" type="java.lang.String">
            <column name="book_code" length="20" not-null="true">
                <comment>电子书编号</comment>
            </column>
        </property>
        <property name="bookName" type="java.lang.String">
            <column name="book_name" length="50" />
        </property>
        <property name="bookPath" type="java.lang.String">
            <column name="book_path" length="100" />
        </property>
        <property name="realFileName" type="java.lang.String">
            <column name="real_file_name" length="100" />
        </property>
        <property name="secret" type="java.lang.String">
            <column name="secret_flag" length="10" />
        </property>
        <property name="bookSize" type="java.lang.Integer">
            <column name="book_size" />
        </property>
        <property name="createTime" type="java.sql.Timestamp">
            <column name="create_time" length="19">
                <comment>加密后入库时间</comment>
            </column>
        </property>
        <property name="uploadTime" type="java.sql.Timestamp">
            <column name="upload_time" length="19">
                <comment>上传到文件服务器时间</comment>
            </column>
        </property>
        <property name="version" type="java.lang.Double">
            <column name="version" precision="2" />
        </property>
        <property name="bookType" type="java.lang.String">
            <column name="book_type" length="4" />
        </property>
        <property name="bookKey" type="java.lang.String">
            <column name="book_key" length="50" />
        </property>
        <property name="bookUrl" type="java.lang.String">
            <column name="book_url" length="100" />
        </property>
        <property name="operator" type="java.lang.String">
            <column name="operator" length="50" />
        </property>
        <property name="serVersion" type="java.lang.String">
            <column name="ser_version" length="10" />
        </property>
        <property name="eduVersion" type="java.lang.String">
            <column name="edu_version" length="10" />
        </property>
        <property name="subject" type="java.lang.String">
            <column name="subject" length="20" />
        </property>
        <property name="edition" type="java.lang.String">
            <column name="edition" length="20" />
        </property>
         <property name="pageNumber" type="java.lang.Integer">
            <column name="page_number" />
        </property>
        <property name="author" type="java.lang.String">
            <column name="author" length="20" />
        </property>
        <property name="publishing" type="java.lang.String">
            <column name="publishing" length="50" />
        </property>
        <property name="language" type="java.lang.String">
            <column name="language" length="20" />
        </property>
        <property name="applyObject" type="java.lang.String">
            <column name="apply_object" length="50" />
        </property>
        <property name="productType" type="java.lang.Integer">
            <column name="product_type" />
        </property>
         <property name="volume" type="java.lang.String">
            <column name="volume" length="10">
                <comment>册</comment>
            </column>
        </property>
        <property name="grade" type="java.lang.String">
            <column name="grade" length="20" />
        </property>
        <property name="schoolStage" type="java.lang.Integer">
            <column name="school_stage" />
        </property>
         <property name="teachVersion" type="java.lang.String">
            <column name="teach_version" length="30" />
        </property>
        <property name="gradeCode" type="java.lang.String">
            <column name="grade_code" length="20" />
        </property>
         <property name="auId" type="java.lang.Integer">
            <column name="au_id" />
        </property>
    </class>
</hibernate-mapping>
